vidsz/__init__.py
vidsz/interfaces/__init__.py
vidsz/interfaces/reader.py
vidsz/interfaces/writer.py
vidsz/opencv/__init__.py
vidsz/opencv/reader/__init__.py
vidsz/opencv/reader/base_reader.py
vidsz/opencv/writer/__init__.py
vidsz/opencv/writer/base_writer.py
vidsz_deployment_test-0.1.0.dist-info/LICENSE
vidsz_deployment_test-0.1.0.dist-info/METADATA
vidsz_deployment_test-0.1.0.dist-info/WHEEL
vidsz_deployment_test-0.1.0.dist-info/top_level.txt
vidsz_deployment_test-0.1.0.dist-info/RECORD
